pythondata_cpu_cv32e41p/__init__.py
pythondata_cpu_cv32e41p/system_verilog/.dir-locals.el
pythondata_cpu_cv32e41p/system_verilog/.gitignore
pythondata_cpu_cv32e41p/system_verilog/.gitlab-ci.yml
pythondata_cpu_cv32e41p/system_verilog/.travis.yml
pythondata_cpu_cv32e41p/system_verilog/Bender.yml
pythondata_cpu_cv32e41p/system_verilog/CONTRIBUTING.md
pythondata_cpu_cv32e41p/system_verilog/LICENSE
pythondata_cpu_cv32e41p/system_verilog/README.md
pythondata_cpu_cv32e41p/system_verilog/cv32e41p_manifest.flist
pythondata_cpu_cv32e41p/system_verilog/src_files.yml
pythondata_cpu_cv32e41p/system_verilog/.github/ISSUE_TEMPLATE/bug.md
pythondata_cpu_cv32e41p/system_verilog/.github/ISSUE_TEMPLATE/config.yml
pythondata_cpu_cv32e41p/system_verilog/.github/ISSUE_TEMPLATE/enhancement.md
pythondata_cpu_cv32e41p/system_verilog/.github/ISSUE_TEMPLATE/question.md
pythondata_cpu_cv32e41p/system_verilog/.github/ISSUE_TEMPLATE/task.md
pythondata_cpu_cv32e41p/system_verilog/bhv/cv32e41p_apu_tracer.sv
pythondata_cpu_cv32e41p/system_verilog/bhv/cv32e41p_core_log.sv
pythondata_cpu_cv32e41p/system_verilog/bhv/cv32e41p_instr_trace.svh
pythondata_cpu_cv32e41p/system_verilog/bhv/cv32e41p_sim_clock_gate.sv
pythondata_cpu_cv32e41p/system_verilog/bhv/cv32e41p_tracer.sv
pythondata_cpu_cv32e41p/system_verilog/bhv/cv32e41p_wrapper.sv
pythondata_cpu_cv32e41p/system_verilog/bhv/include/cv32e41p_tracer_pkg.sv
pythondata_cpu_cv32e41p/system_verilog/ci/Jenkinsfile
pythondata_cpu_cv32e41p/system_verilog/ci/build-riscv-gcc.sh
pythondata_cpu_cv32e41p/system_verilog/ci/download-pulp-gcc.sh
pythondata_cpu_cv32e41p/system_verilog/ci/get-openocd.sh
pythondata_cpu_cv32e41p/system_verilog/ci/install-verilator.sh
pythondata_cpu_cv32e41p/system_verilog/ci/make-tmp.sh
pythondata_cpu_cv32e41p/system_verilog/ci/openocd-to-junit.py
pythondata_cpu_cv32e41p/system_verilog/ci/run-openocd-compliance.sh
pythondata_cpu_cv32e41p/system_verilog/ci/rv32tests-to-junit.py
pythondata_cpu_cv32e41p-0.0.post1883.dist-info/LICENSE
pythondata_cpu_cv32e41p-0.0.post1883.dist-info/METADATA
pythondata_cpu_cv32e41p-0.0.post1883.dist-info/WHEEL
pythondata_cpu_cv32e41p-0.0.post1883.dist-info/top_level.txt
pythondata_cpu_cv32e41p-0.0.post1883.dist-info/RECORD
