Metadata-Version: 2.1
Name: pythondata-cpu-cv32e41p
Version: 0.0.post1883
Summary: Python module containing system_verilog files for CV32E41P cpu.
Home-page: https://github.com/litex-hub/pythondata-cpu-cv32e41p
Author: LiteX Authors
Author-email: litex@googlegroups.com
Project-URL: Bug Tracker, https://github.com/litex-hub/pythondata-cpu-cv32e41p/issues
Project-URL: Source Code, https://github.com/litex-hub/pythondata-cpu-cv32e41p
Classifier: Programming Language :: Python :: 3
Classifier: License :: OSI Approved :: Apache Software License
Classifier: Operating System :: OS Independent
Requires-Python: >=3.5
License-File: LICENSE
